[
 {
  "id": 1,
  "firstName": "Sebastián",
  "lastName": "Braga",
  "email": "sebabraga01@gmail.com",
  "password": "$2a$10$n2DQbKf0uIvB/RYH6.WY/.o6e3scnGHxGRqFS21DjitRr58AChWYq",
  "category": "cliente",
  "image": "avatar.jpg"
 },
 {
  "id": 2,
  "firstName": "Camila Luz",
  "lastName": "Quispe",
  "email": "quispeluzcami@gmail.com",
  "password": "$2a$10$n2DQbKf0uIvB/RYH6.WY/.o6e3scnGHxGRqFS21DjitRr58AChWYq",
  "category": "cliente",
  "image": "avatar.jpg"
 },
 {
  "id": 3,
  "firstName": "Gustavo Fabian",
  "lastName": "Buscalia",
  "email": "buscaliag@gmail.com",
  "password": "$2a$10$n2DQbKf0uIvB/RYH6.WY/.o6e3scnGHxGRqFS21DjitRr58AChWYq",
  "category": "cliente",
  "image": "avatar.jpg"
 },
 {
  "id": 4,
  "firstName": "Valentino",
  "lastName": "Becerine",
  "email": "valentinobecerine@gmail.com",
  "password": "$2a$10$n2DQbKf0uIvB/RYH6.WY/.o6e3scnGHxGRqFS21DjitRr58AChWYq",
  "category": "cliente",
  "image": "avatar.jpg"
 },
 {
  "id": 5,
  "firstName": "Admin",
  "lastName": "del Sitio",
  "email": "admin@gmail.com",
  "password": "$2a$10$n2DQbKf0uIvB/RYH6.WY/.o6e3scnGHxGRqFS21DjitRr58AChWYq",
  "category": "admin",
  "image": "avatar.jpg"
 },
 {
  "id": 6,
  "firstName": "Andrés",
  "lastName": "Iniesta",
  "email": "ainiesta@gmail.com",
  "category": "cliente",
  "password": "$2a$10$LDUj6c7jfP5UulL7fZMkxedsEHSXz5AEc0MOp8TEZk5kYcuRlp54K",
  "image": "img-iniesta-1676042688859.jpg"
 }
]